README
setup.py
abstractclass/__init__.py
abstractclass/abstractActuatorFactory.py
abstractclass/abstractEvent.py
abstractclass/abstractSensorFactory.py
abstractclass/accelerometerSensor.py
abstractclass/actuator.py
abstractclass/altitudeSensor.py
abstractclass/dcMotorActuator.py
abstractclass/eventObserver.py
abstractclass/humiditySensor.py
abstractclass/lightSensor.py
abstractclass/magnetometerSensor.py
abstractclass/motionSensor.py
abstractclass/motorActuator.py
abstractclass/pressureSensor.py
abstractclass/sensor.py
abstractclass/servoMotorActuator.py
abstractclass/stepperMotorActuator.py
abstractclass/temperatureSensor.py
abstractclass/ultrasonicSensor.py
compositesensor/__init__.py
compositesensor/bmp085Composite.py
compositesensor/dht11Composite.py
compositesensor/dht22Composite.py
compositesensor/lsm303dComposite.py
concreteactuator/__init__.py
concreteactuator/stepper28BJY48.py
concreteevent/__init__.py
concreteevent/temperatureEvent.py
concretefactory/__init__.py
concretefactory/accelerometerSensorFactory.py
concretefactory/altitudeSensorFactory.py
concretefactory/compositeSensorFactory.py
concretefactory/humiditySensorFactory.py
concretefactory/lightSensorFactory.py
concretefactory/magnetometerSensorFactory.py
concretefactory/motionSensorFactory.py
concretefactory/pressureSensorFactory.py
concretefactory/stepperMotorActuatorFactory.py
concretefactory/temperatureSensorFactory.py
concretefactory/ultrasonicSensorFactory.py
concreteobserver/__init__.py
concreteobserver/currentConditionDisplay.py
concretesensor/__init__.py
concretesensor/adxl345.py
concretesensor/bmp085Altitude.py
concretesensor/bmp085Pressure.py
concretesensor/bmp085Temperature.py
concretesensor/dht11Humidity.py
concretesensor/dht11Temperature.py
concretesensor/dht22Humidity.py
concretesensor/dht22Temperature.py
concretesensor/hmc5883l.py
concretesensor/hysrf05.py
concretesensor/lsm303dAccelerometer.py
concretesensor/lsm303dMagnetometer.py
concretesensor/parallaxPing.py
concretesensor/pir.py
libsensorPy.egg-info/PKG-INFO
libsensorPy.egg-info/SOURCES.txt
libsensorPy.egg-info/dependency_links.txt
libsensorPy.egg-info/top_level.txt
