Metadata-Version: 1.1
Name: libsensorPy
Version: 0.0.9
Summary: An extendable python library to manipulate sensors coupled to the Raspberry Pi
Home-page: https://github.com/juniorug/libsensorPy
Author: Junior Mascarenhas
Author-email: juniorug@gmail.com
License: BSD
Keywords: example documentation tutorial
Platform: UNKNOWN
Classifier: Development Status :: 3 - Alpha
Classifier: Topic :: Utilities
Classifier: License :: OSI Approved :: BSD License
